kraken/__init__.py
kraken/align.py
kraken/binarization.py
kraken/blla.mlmodel
kraken/blla.py
kraken/containers.py
kraken/iso15924.json
kraken/kraken.py
kraken/pageseg.py
kraken/repo.py
kraken/rpred.py
kraken/serialization.py
kraken/contrib/add_neural_ro.py
kraken/contrib/baselineset_overlay.py
kraken/contrib/extract_lines.py
kraken/contrib/forced_alignment_overlay.py
kraken/contrib/generate_scripts.py
kraken/contrib/heatmap_overlay.py
kraken/contrib/new_classes.json
kraken/contrib/print_word_spreader.py
kraken/contrib/recognition_boxes.py
kraken/contrib/repolygonize.py
kraken/contrib/segmentation_overlay.py
kraken/contrib/set_seg_options.py
kraken/contrib/test_per_file.py
kraken/ketos/__init__.py
kraken/ketos/dataset.py
kraken/ketos/pretrain.py
kraken/ketos/recognition.py
kraken/ketos/repo.py
kraken/ketos/ro.py
kraken/ketos/segmentation.py
kraken/ketos/util.py
kraken/lib/__init__.py
kraken/lib/arrow_dataset.py
kraken/lib/codec.py
kraken/lib/ctc_decoder.py
kraken/lib/default_specs.py
kraken/lib/exceptions.py
kraken/lib/functional_im_transforms.py
kraken/lib/layers.py
kraken/lib/lineest.py
kraken/lib/log.py
kraken/lib/models.py
kraken/lib/morph.py
kraken/lib/progress.py
kraken/lib/register.py
kraken/lib/segmentation.py
kraken/lib/sl.py
kraken/lib/train.py
kraken/lib/util.py
kraken/lib/vgsl.py
kraken/lib/xml.py
kraken/lib/dataset/__init__.py
kraken/lib/dataset/recognition.py
kraken/lib/dataset/ro.py
kraken/lib/dataset/scripts.json
kraken/lib/dataset/segmentation.py
kraken/lib/dataset/utils.py
kraken/lib/pretrain/__init__.py
kraken/lib/pretrain/layers.py
kraken/lib/pretrain/model.py
kraken/lib/pretrain/util.py
kraken/lib/ro/__init__.py
kraken/lib/ro/layers.py
kraken/lib/ro/model.py
kraken/lib/ro/util.py
kraken/templates/abbyyxml
kraken/templates/alto
kraken/templates/hocr
kraken/templates/layout.html
kraken/templates/main.js
kraken/templates/pagexml
kraken/templates/report
kraken/templates/style.css
kraken-6.0.3.dist-info/AUTHORS
kraken-6.0.3.dist-info/LICENSE
kraken-6.0.3.dist-info/METADATA
kraken-6.0.3.dist-info/WHEEL
kraken-6.0.3.dist-info/entry_points.txt
kraken-6.0.3.dist-info/pbr.json
kraken-6.0.3.dist-info/top_level.txt
kraken-6.0.3.dist-info/RECORD
