Metadata-Version: 2.1
Name: kraken
Version: 6.0.3
Summary: OCR/HTR engine for all the languages
Home-page: https://kraken.re
Author: Benjamin Kiessling
Author-email: mittagessen@l.unchti.me
License: Apache
Keywords: ocr,htr
Classifier: Development Status :: 5 - Production/Stable
Classifier: Environment :: Console
Classifier: Environment :: GPU
Classifier: Intended Audience :: Science/Research
Classifier: License :: OSI Approved :: Apache Software License
Classifier: Operating System :: POSIX
Classifier: Programming Language :: Python :: 3.9
Classifier: Programming Language :: Python :: 3.10
Classifier: Programming Language :: Python :: 3.11
Classifier: Programming Language :: Python :: 3.12
Classifier: Topic :: Scientific/Engineering :: Image Recognition
Classifier: Topic :: Scientific/Engineering :: Artificial Intelligence
Requires-Python: <3.13,>=3.9
License-File: LICENSE
License-File: AUTHORS
Requires-Dist: jsonschema
Requires-Dist: lxml
Requires-Dist: requests
Requires-Dist: click<8.3,>=8.1
Requires-Dist: numpy~=2.0.0
Requires-Dist: Pillow>=9.2.0
Requires-Dist: regex
Requires-Dist: scipy~=1.13.0
Requires-Dist: protobuf>=3.0.0
Requires-Dist: coremltools~=8.1
Requires-Dist: jinja2~=3.0
Requires-Dist: python-bidi~=0.6.0
Requires-Dist: torchvision>=0.5.0
Requires-Dist: torch<=2.9,>=2.4.0
Requires-Dist: scikit-learn~=1.5.0
Requires-Dist: scikit-image~=0.24.0
Requires-Dist: shapely>=2.0.6,~=2.0.6
Requires-Dist: pyarrow
Requires-Dist: htrmopo>=0.3,~=0.3
Requires-Dist: lightning~=2.4.0
Requires-Dist: torchmetrics>=1.1.0
Requires-Dist: threadpoolctl~=3.5.0
Requires-Dist: platformdirs
Requires-Dist: rich<14.1.0
Requires-Dist: iso639-lang
Provides-Extra: augment
Requires-Dist: albumentations; extra == "augment"
Provides-Extra: pdf
Requires-Dist: pyvips; extra == "pdf"
Provides-Extra: test
Requires-Dist: hocr-spec; extra == "test"
Requires-Dist: pytest; extra == "test"
